fumes/__init__.py
fumes/utils.py
fumes/components/__init__.py
fumes/components/base.py
fumes/components/button.py
fumes/components/textbox.py
fumes/frontend/static/css/fumes.css
fumes/frontend/static/js/fumes.js
fumes/frontend/templates/base.html
fumes-0.1.0.dist-info/licenses/LICENSE
fumes-0.1.0.dist-info/METADATA
fumes-0.1.0.dist-info/WHEEL
fumes-0.1.0.dist-info/entry_points.txt
fumes-0.1.0.dist-info/top_level.txt
fumes-0.1.0.dist-info/RECORD
